okx_candle/__init__.py
okx_candle/utils.py
okx_candle/code/__init__.py
okx_candle/exception/__init__.py
okx_candle/exception/_base.py
okx_candle/exception/param.py
okx_candle/exception/req.py
okx_candle/exception/rule.py
okx_candle/market/__init__.py
okx_candle/market/_base.py
okx_candle/market/exchange_info.py
okx_candle/market/history_candle.py
okx_candle/market/ticker.py
okx_candle/server/__init__.py
okx_candle/server/rule.py
okx_candle/server/server.py
okx_candle-2.0.1.dist-info/METADATA
okx_candle-2.0.1.dist-info/WHEEL
okx_candle-2.0.1.dist-info/top_level.txt
okx_candle-2.0.1.dist-info/RECORD
