Metadata-Version: 2.1
Name: okx-candle
Version: 2.0.1
Summary: OKX local and real-time market candle server
Home-page: https://github.com/pyted/okx_candle
Author: pyted
Author-email: pyted@outlook.com
License: MIT
Classifier: License :: OSI Approved :: MIT License
Classifier: Programming Language :: Python
Classifier: Programming Language :: Python :: 3
Classifier: Programming Language :: Python :: 3.6
Classifier: Programming Language :: Python :: Implementation :: CPython
Classifier: Programming Language :: Python :: Implementation :: PyPy
Requires-Python: >=3.6.0
Requires-Dist: pendulum
Requires-Dist: numpy
Requires-Dist: pandas
Requires-Dist: requests
Requires-Dist: candlelite
Requires-Dist: okx
Requires-Dist: paux
